cyclic/__init__.py
cyclic/a.py
cyclic_a-0.0.2.dist-info/LICENSE
cyclic_a-0.0.2.dist-info/METADATA
cyclic_a-0.0.2.dist-info/WHEEL
cyclic_a-0.0.2.dist-info/top_level.txt
cyclic_a-0.0.2.dist-info/RECORD
